MANIFEST.in
README.md
requirements.txt
setup.cfg
setup.py
bigbench/__init__.py
bigbench/evaluate_task.py
bigbench.egg-info/PKG-INFO
bigbench.egg-info/SOURCES.txt
bigbench.egg-info/dependency_links.txt
bigbench.egg-info/requires.txt
bigbench.egg-info/top_level.txt
bigbench/api/__init__.py
bigbench/api/analysis.py
bigbench/api/conftest.py
bigbench/api/json_task.py
bigbench/api/json_utils.py
bigbench/api/model.py
bigbench/api/results.py
bigbench/api/task.py
bigbench/api/task_metrics.py
bigbench/api/test_analysis.py
bigbench/api/test_json_utils.py
bigbench/api/test_results.py
bigbench/api/test_task_metrics.py
bigbench/api/test_tasks.py
bigbench/api/test_util.py
bigbench/api/util.py
bigbench/bbseqio/__init__.py
bigbench/bbseqio/bigbench_bridge.py
bigbench/bbseqio/bigbench_bridge_test.py
bigbench/bbseqio/bigbench_json_paths.py
bigbench/bbseqio/bigbench_json_paths_test.py
bigbench/bbseqio/bigbench_lite.py
bigbench/bbseqio/compatibility_test.py
bigbench/bbseqio/run_example.py
bigbench/bbseqio/task_api.py
bigbench/bbseqio/task_api_test.py
bigbench/bbseqio/tasks.py
bigbench/bbseqio/test_utils.py
bigbench/bbseqio/utils.py
bigbench/bbseqio/utils_test.py
bigbench/bbseqio/vocabs.py
bigbench/benchmark_tasks/__init__.py
bigbench/benchmark_tasks/task_authors.tsv
bigbench/benchmark_tasks/task_human_eval.pkl
bigbench/benchmark_tasks/task_metadata.json
bigbench/benchmark_tasks/abstract_narrative_understanding/task.json
bigbench/benchmark_tasks/abstract_narrative_understanding/utils.py
bigbench/benchmark_tasks/abstract_narrative_understanding/4_distractors/task.json
bigbench/benchmark_tasks/abstract_narrative_understanding/99_distractors/task.json
bigbench/benchmark_tasks/abstract_narrative_understanding/9_distractors/task.json
bigbench/benchmark_tasks/abstraction_and_reasoning_corpus/task.py
bigbench/benchmark_tasks/abstraction_and_reasoning_corpus/data/evaluation/00576224.json
bigbench/benchmark_tasks/abstraction_and_reasoning_corpus/data/evaluation/009d5c81.json
bigbench/benchmark_tasks/abstraction_and_reasoning_corpus/data/evaluation/00dbd492.json
bigbench/benchmark_tasks/abstraction_and_reasoning_corpus/data/evaluation/03560426.json
