Metadata-Version: 2.1
Name: bigbench
Version: 1.0.0
Summary: A collaborative benchmark intended to probe large language models and extrapolate their future capabilities.
Home-page: UNKNOWN
Author: The BIG-Bench Language Models Benchmark team.
Author-email: bigbench@google.com
License: UNKNOWN
Platform: UNKNOWN
